mojang_api/__init__.py
mojang_api/_common/__init__.py
mojang_api/_common/endpoint.py
mojang_api/_common/player.py
mojang_api/_common/response.py
mojang_api/servers/__init__.py
mojang_api/servers/api.py
mojang_api/servers/authserver.py
mojang_api/servers/sessionserver.py
mojang_api/servers/status.py
mojang_api/user/__init__.py
mojang_api/user/player.py
mojang_api/utils/__init__.py
mojang_api/utils/uuid.py
mojang_api_3-3.0.4.dist-info/METADATA
mojang_api_3-3.0.4.dist-info/RECORD
mojang_api_3-3.0.4.dist-info/WHEEL
mojang_api_3-3.0.4.dist-info/top_level.txt
