Metadata-Version: 1.2
Name: mojang-api-3
Version: 3.0.4
Summary: A full Python wrapper of Mojang's API and Authentication API.
Home-page: https://github.com/Kiln707/mojang-api
Author: Synchronous, Kiln707
License: MIT
Keywords: mojang minecraft mc api authentication auth
Platform: UNKNOWN
Classifier: Development Status :: 4 - Beta
Classifier: Intended Audience :: Developers
Classifier: Topic :: Software Development :: Libraries :: Python Modules
Classifier: License :: OSI Approved :: MIT License
Classifier: Programming Language :: Python :: 3
Classifier: Programming Language :: Python :: 3.5
Classifier: Programming Language :: Python :: 3.6
Requires-Python: >=3.5.*
